{
  "users": [
    { "id": "IBCS2bch", "webSockets": [] },
    { "id": "IBCSx823", "webSockets": [] },
    { "id": "IBCSv7Nz", "webSockets": [] },
    { "id": "ABCDEFxlq64j", "webSockets": [] },
    { "id": "IBCSnda1", "webSockets": [] },
    { "id": "IBCSilwN", "webSockets": [] },
    { "id": "DixK7", "webSockets": [] },
    { "id": "AJ2WH", "webSockets": [] },
    { "id": "lROHT", "webSockets": [] },
    { "id": "icWg4", "webSockets": [] },
    { "id": "Marcelo", "webSockets": [] }
  ],
  "channels": [],
  "bots": [
    {
      "name": "WebWidgetChannel",
      "description": "WebWidget Stuff",
      "secretKey": "f93CBfCG6aoz9ZceXHJACoPXqpy5unVx",
      "uri": "https://e8af89b5.ngrok.io/connectors/v1/tenants/chatbot-tenant/listeners/webhook/channels/7CB756BB-C288-40A4-846D-870D501F62D3",
      "type": "webhook",
      "tenantId": "chatbot-tenant",
      "id": "7CB756BB-C288-40A4-846D-870D501F62D3"
    },
    {
      "name": "iOSChannel",
      "description": "iOS Stuff",
      "secretKey": "XzG4FTfHa1Aqd2MuAHx7SAIH6WJfnGBy",
      "uri":
        "http://localhost:8800/connectors/v1/tenants/chatbot-tenant/listeners/webhook/channels/BF5E021B-ABAC-42A1-B618-415160078A1F",
      "type": "webhook",
      "tenantId": "chatbot-tenant",
      "id": "BF5E021B-ABAC-42A1-B618-415160078A1F"
    }
  ],
  "nextWebSocketID": 168
}
